pretix_wallets/__init__.py
pretix_wallets/apps.py
pretix_wallets/forms.py
pretix_wallets/googleeventticket.py
pretix_wallets/signals.py
pretix_wallets/ticketoutput.py
pretix_wallets/locale/de/LC_MESSAGES/django.mo
pretix_wallets/locale/de/LC_MESSAGES/django.po
pretix_wallets/locale/de_Informal/.gitkeep
pretix_wallets/locale/de_Informal/LC_MESSAGES/django.mo
pretix_wallets/locale/de_Informal/LC_MESSAGES/django.po
pretix_wallets/static/pretix_wallets/.gitkeep
pretix_wallets/templates/pretix_wallets/.gitkeep
pretix_wallets-1.0.0.dist-info/LICENSE
pretix_wallets-1.0.0.dist-info/METADATA
pretix_wallets-1.0.0.dist-info/WHEEL
pretix_wallets-1.0.0.dist-info/entry_points.txt
pretix_wallets-1.0.0.dist-info/top_level.txt
pretix_wallets-1.0.0.dist-info/RECORD
