Metadata-Version: 2.1
Name: pretix-wallets
Version: 1.0.0
Summary: Allow users to save the ticket into wallet apps
Author-email: Robin Ferch <hi@robinferch.me>
Maintainer-email: Robin Ferch <hi@robinferch.me>
License: Apache
Project-URL: homepage, https://github.com/Nachwahl/pretix-wallets
Project-URL: repository, https://github.com/Nachwahl/pretix-wallets
Keywords: pretix
License-File: LICENSE
Requires-Dist: google-auth
